api_ai/__init__.py
api_ai/api.py
api_ai/cli.py
api_ai/models.py
api_ai/schema_handlers.py
flask_assistant/__init__.py
flask_assistant/core.py
flask_assistant/hass.py
flask_assistant/manager.py
flask_assistant/utils.py
flask_assistant/response/__init__.py
flask_assistant/response/actions.py
flask_assistant/response/base.py
flask_assistant/response/df_messenger.py
flask_assistant/response/dialogflow.py
flask_assistant/response/hangouts.py
Flask_Assistant-0.5.4.dist-info/LICENSE.txt
Flask_Assistant-0.5.4.dist-info/METADATA
Flask_Assistant-0.5.4.dist-info/WHEEL
Flask_Assistant-0.5.4.dist-info/entry_points.txt
Flask_Assistant-0.5.4.dist-info/top_level.txt
Flask_Assistant-0.5.4.dist-info/RECORD
