Metadata-Version: 2.1
Name: Flask-Assistant
Version: 0.5.4
Summary: Framework for Building Virtual Assistants with Dialogflow
Home-page: https://github.com/treethought/flask-assistant
Author: Cam Sweeney
Author-email: cpsweene@gmail.com
License: Apache 2.0
Platform: any
Classifier: License :: OSI Approved :: Apache Software License
Classifier: Framework :: Flask
Classifier: Programming Language :: Python
Classifier: Environment :: Web Environment
Classifier: Intended Audience :: Developers
Classifier: Operating System :: OS Independent
Classifier: Topic :: Internet :: WWW/HTTP :: Dynamic Content
Classifier: Topic :: Software Development :: Libraries :: Python Modules
Requires-Dist: Flask
Requires-Dist: requests
Requires-Dist: ruamel.yaml
Requires-Dist: aniso8601
Requires-Dist: google-auth
Requires-Dist: dialogflow
Provides-Extra: hassremote
Requires-Dist: homeassistant (>=0.37.1) ; extra == 'hassremote'
